syncclient/__init__.py
syncclient/client.py
syncclient/main.py
syncclient-0.8.0.dist-info/DESCRIPTION.rst
syncclient-0.8.0.dist-info/METADATA
syncclient-0.8.0.dist-info/RECORD
syncclient-0.8.0.dist-info/WHEEL
syncclient-0.8.0.dist-info/metadata.json
syncclient-0.8.0.dist-info/pbr.json
syncclient-0.8.0.dist-info/top_level.txt
tests/__init__.py
tests/support.py
tests/test_client.py
