Metadata-Version: 2.0
Name: syncclient
Version: 0.8.0
Summary: Firefox Sync client
Home-page: https://github.com/mozilla-services/syncclient
Author: Mozilla Services
Author-email: services-dev@mozilla.com
License: Apache License (2.0)
Keywords: web services
Platform: UNKNOWN
Classifier: Programming Language :: Python
Classifier: Programming Language :: Python :: 2
Classifier: Programming Language :: Python :: 2.7
Classifier: Programming Language :: Python :: 3
Classifier: Programming Language :: Python :: 3.4
Classifier: Programming Language :: Python :: 3.5
Classifier: Topic :: Internet :: WWW/HTTP
Classifier: Topic :: Internet :: WWW/HTTP :: WSGI :: Application
Classifier: License :: OSI Approved :: Apache Software License
Requires-Dist: PyFxA
Requires-Dist: requests
Requires-Dist: requests-hawk
Requires-Dist: six
